blue_stability/__init__.py
blue_stability/__main__.py
blue_stability/logger.py
blue_stability/urls.py
blue_stability/.abcli/actions.sh
blue_stability/.abcli/aiart.sh
blue_stability/.abcli/aka.sh
blue_stability/.abcli/blue_stability.sh
blue_stability/.abcli/generate_function.sh
blue_stability/.abcli/tests/version.sh
blue_stability-4.48.1.dist-info/LICENSE
blue_stability-4.48.1.dist-info/METADATA
blue_stability-4.48.1.dist-info/WHEEL
blue_stability-4.48.1.dist-info/top_level.txt
blue_stability-4.48.1.dist-info/RECORD
