Metadata-Version: 2.1
Name: blue_stability
Version: 4.48.1
Summary: 🟦 a command interface to stability.ai.
Home-page: https://github.com/kamangir/blue-stability
Author: Arash Abadpour (Kamangir)
Author-email: arash@kamangir.net
License: Public Domain
Classifier: Programming Language :: Python :: 3
Classifier: Programming Language :: Unix Shell
Classifier: License :: Public Domain
Classifier: Operating System :: OS Independent
License-File: LICENSE
Requires-Dist: blueness
Requires-Dist: abcli
Requires-Dist: boto3
Requires-Dist: emoji
Requires-Dist: geojson
Requires-Dist: geopandas
Requires-Dist: matplotlib
Requires-Dist: opencv-python
Requires-Dist: pymysql==0.10.1
Requires-Dist: pyyaml
Requires-Dist: pylint
Requires-Dist: pytest
Requires-Dist: python-dotenv[cli]
Requires-Dist: stability-sdk
Requires-Dist: tqdm
Requires-Dist: torchvision
